w32lex/__init__.py
w32lex-1.0.9.dist-info/LICENSE
w32lex-1.0.9.dist-info/METADATA
w32lex-1.0.9.dist-info/WHEEL
w32lex-1.0.9.dist-info/top_level.txt
w32lex-1.0.9.dist-info/RECORD
