Metadata-Version: 2.2
Name: w32lex
Version: 1.0.9
Summary: Equivalent shlex module for the Win32 world
Author-email: maxpat78 <maxpat78@yahoo.it>
License: Apache License
Project-URL: Homepage, https://github.com/maxpat78/w32lex
Project-URL: Source, https://github.com/maxpat78/w32lex
Keywords: argument-parser,split,python,python3,win32,splitter,shlex,lexer-parser,argument-parsing
Classifier: Development Status :: 4 - Beta
Classifier: Intended Audience :: Developers
Classifier: License :: OSI Approved :: Apache Software License
Classifier: Programming Language :: Python :: 3 :: Only
Requires-Python: >=3.0
License-File: LICENSE
